{
    "_comment": [
        "The builds defined in this file should not contain tests, ",
        "and the file should not contain builds that are essentially tests. ",
        "The only builds in this file should be the builds necessary to produce ",
        "release artifacts. ",
        "Tests to run on linux hosts should go in one of the other linux_ build ",
        "definition files."
    ],
    "luci_flags": {
      "upload_content_hash": true
    },
    "builds": [
        {
            "archives": [
                {
                    "name": "ci/linux_profile_riscv64",
                    "type": "gcs",
                    "base_path": "out/ci/linux_profile_riscv64/zip_archives/",
                    "include_paths": [
                        "out/ci/linux_profile_riscv64/zip_archives/linux-riscv64-profile/linux-riscv64-flutter-gtk.zip"
                    ],
                    "realm": "production"
                }
            ],
            "drone_dimensions": [
                "device_type=none",
                "os=Linux"
            ],
            "gclient_variables": {
                "download_android_deps": false,
                "download_jdk": false,
                "use_rbe": true
            },
            "gn": [
                "--target-dir",
                "ci/linux_profile_riscv64",
                "--runtime-mode",
                "profile",
                "--target-os=linux",
                "--linux-cpu=riscv64",
                "--prebuilt-dart-sdk",
                "--no-lto",
                "--rbe",
                "--no-goma"
            ],
            "name": "ci/linux_profile_riscv64",
            "description": "Produces profile mode artifacts to target riscv64 Linux from a Linux host.",
            "ninja": {
                "config": "ci/linux_profile_riscv64",
                "targets": [
                    "flutter/shell/platform/linux:flutter_gtk"
                ]
            }
        },
        {
            "archives": [
                {
                    "name": "ci/linux_debug_riscv64",
                    "type": "gcs",
                    "base_path": "out/ci/linux_debug_riscv64/zip_archives/",
                    "include_paths": [
                        "out/ci/linux_debug_riscv64/zip_archives/linux-riscv64/artifacts.zip",
                        "out/ci/linux_debug_riscv64/zip_archives/linux-riscv64/impeller_sdk.zip",
                        "out/ci/linux_debug_riscv64/zip_archives/linux-riscv64/linux-riscv64-embedder.zip",
                        "out/ci/linux_debug_riscv64/zip_archives/linux-riscv64/font-subset.zip",
                        "out/ci/linux_debug_riscv64/zip_archives/linux-riscv64-debug/linux-riscv64-flutter-gtk.zip",
                        "out/ci/linux_debug_riscv64/zip_archives/dart-sdk-linux-riscv64.zip"
                    ],
                    "realm": "production"
                }
            ],
            "drone_dimensions": [
                "device_type=none",
                "os=Linux"
            ],
            "gclient_variables": {
                "download_android_deps": false,
                "download_jdk": false,
                "use_rbe": true
            },
            "gn": [
                "--target-dir",
                "ci/linux_debug_riscv64",
                "--runtime-mode",
                "debug",
                "--target-os=linux",
                "--linux-cpu=riscv64",
                "--prebuilt-dart-sdk",
                "--no-lto",
                "--rbe",
                "--no-goma"
            ],
            "name": "ci/linux_debug_riscv64",
            "description": "Produces debug mode artifacts to target riscv64 Linux from a Linux host.",
            "ninja": {
                "config": "ci/linux_debug_riscv64",
                "targets": [
                    "flutter/build/archives:artifacts",
                    "flutter/build/archives:dart_sdk_archive",
                    "flutter/tools/font_subset",
                    "flutter/shell/platform/linux:flutter_gtk",
                    "flutter/impeller/toolkit/interop:sdk",
                    "flutter/build/archives:embedder"
                ]
            }
        },
        {
            "archives": [
                {
                    "name": "ci/linux_release_riscv64",
                    "type": "gcs",
                    "base_path": "out/ci/linux_release_riscv64/zip_archives/",
                    "include_paths": [
                        "out/ci/linux_release_riscv64/zip_archives/linux-riscv64-release/linux-riscv64-flutter-gtk.zip"
                    ],
                    "realm": "production"
                }
            ],
            "drone_dimensions": [
                "device_type=none",
                "os=Linux"
            ],
            "gclient_variables": {
                "download_android_deps": false,
                "download_jdk": false,
                "use_rbe": true
            },
            "gn": [
                "--target-dir",
                "ci/linux_release_riscv64",
                "--runtime-mode",
                "release",
                "--target-os=linux",
                "--linux-cpu=riscv64",
                "--prebuilt-dart-sdk",
                "--no-lto",
                "--rbe",
                "--no-goma"
            ],
            "name": "ci/linux_release_riscv64",
            "description": "Produces release mode artifacts to target riscv64 Linux from a Linux host.",
            "ninja": {
                "config": "ci/linux_release_riscv64",
                "targets": [
                    "flutter/shell/platform/linux:flutter_gtk"
                ]
            }
        }
    ]
}
